Workbook

Sheet Dashboard
A1: NUSANTARA DIGITAL GROUP — Finance Performance Dashboard (FY2025)
A3: Software & Digital Marketing • Influencer Marketing | Ads Management | E-commerce Enablement | SaaS Creator Platform • All figures in IDR millions
A6: TOTAL REVENUE | E6: NET PROFIT | I6: GROSS MARGIN | M6: NET MARGIN
A7: =Monthly_Summary!B17 -> 59186.7 | E7: =Monthly_Summary!H17 -> 14390.6 | I7: =Monthly_Summary!G17/Monthly_Summary!B17 -> 0.5342163 | M7: =Monthly_Summary!H17/Monthly_Summary!B17 -> 0.24313908
A8: IDR mn | E8: IDR mn | I8: of revenue | M8: of revenue
A11: OPEX RATIO | E11: REV GROWTH | I11: AVG ROAS | M11: AVG CAC
A12: =Monthly_Summary!I17/Monthly_Summary!B17 -> 0.75685247 | E12: =(Monthly_Summary!B16-Monthly_Summary!B5)/Monthly_Summary!B5 -> 0.66281427 | I12: =AVERAGE(Raw_Data!L5:L196) -> 4.1817188 | M12: =AVERAGE(Raw_Data!K5:K196) -> 3.7979688
A13: of revenue | E13: Jan→Dec | I13: blended | M13: IDR mn/client
A64: Data simulated for portfolio purposes • Forecast via linear TREND() regression

Sheet Raw_Data
A1: Raw Transaction Data
A2: Source data — 12 months, 4 service lines, 16 clients (IDR millions). Simulated for portfolio.
A4: Month | B4: Service Category | C4: Client Name | D4: Revenue | E4: Operational Cost | F4: Marketing Spend | G4: Employee Cost | H4: Software Subscription Cost | I4: Gross Profit | J4: Net Profit | K4: CAC | L4: ROAS | M4: Budget | N4: Actual Spending
A5: Jan-2025 | B5: Influencer Marketing | C5: Wardah Cosmetics | D5: 278.5 | E5: 120.2 | F5: 25.2 | G5: 40.5 | H5: 8.6 | I5: 158.3 | J5: 84 | K5: 2.92 | L5: 3.88 | M5: 272.3 | N5: 193.3
A6: Jan-2025 | B6: Influencer Marketing | C6: Kopi Kenangan | D6: 199.4 | E6: 83.6 | F6: 19.2 | G6: 28.3 | H6: 5.8 | I6: 115.9 | J6: 62.6 | K6: 3 | L6: 4.07 | M6: 203.1 | N6: 143.2
A7: Jan-2025 | B7: Influencer Marketing | C7: Erigo Apparel | D7: 179.6 | E7: 75.9 | F7: 18.5 | G7: 24.5 | H7: 5.4 | I7: 103.7 | J7: 55.2 | K7: 2.88 | L7: 3.76 | M7: 196.1 | N7: 132.6
A8: Jan-2025 | B8: Influencer Marketing | C8: Somethinc | D8: 197.9 | E8: 81.8 | F8: 18.2 | G8: 28.2 | H8: 5.9 | I8: 116.2 | J8: 63.8 | K8: 2.84 | L8: 4.2 | M8: 189.1 | N8: 142.2
A9: Jan-2025 | B9: Ads Management | C9: Tokopedia | D9: 631.8 | E9: 364.3 | F9: 52.1 | G9: 78.4 | H9: 24.2 | I9: 267.5 | J9: 112.7 | K9: 2.18 | L9: 4.9 | M9: 631.1 | N9: 520.6
A10: Jan-2025 | B10: Ads Management | C10: Traveloka | D10: 185.9 | E10: 106.5 | F10: 14.6 | G10: 22.1 | H10: 7.5 | I10: 79.4 | J10: 35.3 | K10: 2.14 | L10: 5.9 | M10: 178.7 | N10: 160.9
A11: Jan-2025 | B11: Ads Management | C11: Ruangguru | D11: 187.4 | E11: 100.2 | F11: 13.5 | G11: 23.1 | H11: 7.6 | I11: 87.2 | J11: 43 | K11: 2.56 | L11: 5.86 | M11: 180.1 | N11: 144.3
A12: Jan-2025 | B12: Ads Management | C12: BliBli | D12: 410.3 | E12: 235.8 | F12: 34 | G12: 48.9 | H12: 15.7 | I12: 174.5 | J12: 75.9 | K12: 2.26 | L12: 5.27 | M12: 434.7 | N12: 344.5
A13: Jan-2025 | B13: E-commerce Enablement | C13: Eiger Adventure | D13: 182.6 | E13: 87.4 | F13: 14.9 | G13: 23.2 | H13: 8.7 | I13: 95.2 | J13: 48.4 | K13: 4.27 | L13: 3.63 | M13: 187.4 | N13: 142.2
A14: Jan-2025 | B14: E-commerce Enablement | C14: MS Glow | D14: 294 | E14: 140.4 | F14: 28.2 | G14: 37.7 | H14: 14.1 | I14: 153.5 | J14: 73.6 | K14: 3.84 | L14: 3.49 | M14: 320.3 | N14: 231.2
A15: Jan-2025 | B15: E-commerce Enablement | C15: Scarlett Whitening | D15: 231.7 | E15: 116.3 | F15: 22.5 | G15: 29.6 | H15: 12 | I15: 115.4 | J15: 51.3 | K15: 4.15 | L15: 4.08 | M15: 251.3 | N15: 179.5
A16: Jan-2025 | B16: E-commerce Enablement | C16: Sociolla | D16: 360.9 | E16: 168.9 | F16: 32.3 | G16: 48.2 | H16: 18.7 | I16: 192 | J16: 92.8 | K16: 3.49 | L16: 3.81 | M16: 365.5 | N16: 263.9
... A196: Dec-2025 | B196: SaaS Creator Platform | C196: TikTok Shop ID | D196: 312.1 | E196: 96.3 | F196: 47.3 | G196: 61 | H196: 36.5 | I196: 215.8 | J196: 71.1 | K196: 4.91 | L196: 3.08 | M196: 317.6 | N196: 251.2

Sheet Monthly_Summary
A1: Monthly Summary
A2: SUMIF-driven monthly aggregation feeding KPIs, trends and forecast (IDR millions).
A4: Month | B4: Revenue | C4: Operational Cost | D4: Marketing Spend | E4: Employee Cost | F4: Software Cost | G4: Gross Profit | H4: Net Profit | I4: Total OpEx | J4: Budget | L4: Rev Growth % | M4: GP Margin % | N4: NP Margin % | O4: OpEx Ratio %
A5: Jan-2025 | B5: =SUMIF(Raw_Data!$A$5:$A$196,$A5,Raw_Data!$D$5:$D$196) -> 3945.6 | C5: =SUMIF(Raw_Data!$A$5:$A$196,$A5,Raw_Data!$E$5:$E$196) -> 1864.1 | D5: =SUMIF(Raw_Data!$A$5:$A$196,$A5,Raw_Data!$F$5:$F$196) -> 377.4 | E5: =SUMIF(Raw_Data!$A$5:$A$196,$A5,Raw_Data!$G$5:$G$196) -> 554.6 | F5: =SUMIF(Raw_Data!$A$5:$A$196,$A5,Raw_Data!$H$5:$H$196) -> 206.3 | G5: =SUMIF(Raw_Data!$A$5:$A$196,$A5,Raw_Data!$I$5:$I$196) -> 2081.6 | H5: =SUMIF(Raw_Data!$A$5:$A$196,$A5,Raw_Data!$J$5:$J$196) -> 943.2 | I5: =C5+D5+E5+F5 -> 3002.4 | J5: =SUMIF(Raw_Data!$A$5:$A$196,$A5,Raw_Data!$M$5:$M$196) -> 4049.6 | L5: — | M5: =G5/B5 -> 0.52757502 | N5: =H5/B5 -> 0.23905109 | O5: =I5/B5 -> 0.76094891
A6: Feb-2025 | B6: =SUMIF(Raw_Data!$A$5:$A$196,$A6,Raw_Data!$D$5:$D$196) -> 4108 | C6: =SUMIF(Raw_Data!$A$5:$A$196,$A6,Raw_Data!$E$5:$E$196) -> 1929.8 | D6: =SUMIF(Raw_Data!$A$5:$A$196,$A6,Raw_Data!$F$5:$F$196) -> 393.8 | E6: =SUMIF(Raw_Data!$A$5:$A$196,$A6,Raw_Data!$G$5:$G$196) -> 579.8 | F6: =SUMIF(Raw_Data!$A$5:$A$196,$A6,Raw_Data!$H$5:$H$196) -> 221 | G6: =SUMIF(Raw_Data!$A$5:$A$196,$A6,Raw_Data!$I$5:$I$196) -> 2178.3 | H6: =SUMIF(Raw_Data!$A$5:$A$196,$A6,Raw_Data!$J$5:$J$196) -> 983.5 | I6: =C6+D6+E6+F6 -> 3124.4 | J6: =SUMIF(Raw_Data!$A$5:$A$196,$A6,Raw_Data!$M$5:$M$196) -> 4172.8 | L6: =(B6-B5)/B5 -> 0.041159773 | M6: =G6/B6 -> 0.53025803 | N6: =H6/B6 -> 0.23941091 | O6: =I6/B6 -> 0.76056475
A7: Mar-2025 | B7: =SUMIF(Raw_Data!$A$5:$A$196,$A7,Raw_Data!$D$5:$D$196) -> 4804 | C7: =SUMIF(Raw_Data!$A$5:$A$196,$A7,Raw_Data!$E$5:$E$196) -> 2240.8 | D7: =SUMIF(Raw_Data!$A$5:$A$196,$A7,Raw_Data!$F$5:$F$196) -> 477.3 | E7: =SUMIF(Raw_Data!$A$5:$A$196,$A7,Raw_Data!$G$5:$G$196) -> 678.5 | F7: =SUMIF(Raw_Data!$A$5:$A$196,$A7,Raw_Data!$H$5:$H$196) -> 259.3 | G7: =SUMIF(Raw_Data!$A$5:$A$196,$A7,Raw_Data!$I$5:$I$196) -> 2563.2 | H7: =SUMIF(Raw_Data!$A$5:$A$196,$A7,Raw_Data!$J$5:$J$196) -> 1148.1 | I7: =C7+D7+E7+F7 -> 3655.9 | J7: =SUMIF(Raw_Data!$A$5:$A$196,$A7,Raw_Data!$M$5:$M$196) -> 4826.2 | L7: =(B7-B6)/B6 -> 0.16942551 | M7: =G7/B7 -> 0.53355537 | N7: =H7/B7 -> 0.23898834 | O7: =I7/B7 -> 0.76101166
A8: Apr-2025 | B8: =SUMIF(Raw_Data!$A$5:$A$196,$A8,Raw_Data!$D$5:$D$196) -> 5126.9 | C8: =SUMIF(Raw_Data!$A$5:$A$196,$A8,Raw_Data!$E$5:$E$196) -> 2338.6 | D8: =SUMIF(Raw_Data!$A$5:$A$196,$A8,Raw_Data!$F$5:$F$196) -> 487.8 | E8: =SUMIF(Raw_Data!$A$5:$A$196,$A8,Raw_Data!$G$5:$G$196) -> 718.6 | F8: =SUMIF(Raw_Data!$A$5:$A$196,$A8,Raw_Data!$H$5:$H$196) -> 271.9 | G8: =SUMIF(Raw_Data!$A$5:$A$196,$A8,Raw_Data!$I$5:$I$196) -> 2788.6 | H8: =SUMIF(Raw_Data!$A$5:$A$196,$A8,Raw_Data!$J$5:$J$196) -> 1309.9 | I8: =C8+D8+E8+F8 -> 3816.9 | J8: =SUMIF(Raw_Data!$A$5:$A$196,$A8,Raw_Data!$M$5:$M$196) -> 5166.4 | L8: =(B8-B7)/B7 -> 0.067214821 | M8: =G8/B8 -> 0.54391543 | N8: =H8/B8 -> 0.25549552 | O8: =I8/B8 -> 0.74448497
A9: May-2025 | B9: =SUMIF(Raw_Data!$A$5:$A$196,$A9,Raw_Data!$D$5:$D$196) -> 4425.8 | C9: =SUMIF(Raw_Data!$A$5:$A$196,$A9,Raw_Data!$E$5:$E$196) -> 2090.1 | D9: =SUMIF(Raw_Data!$A$5:$A$196,$A9,Raw_Data!$F$5:$F$196) -> 433.5 | E9: =SUMIF(Raw_Data!$A$5:$A$196,$A9,Raw_Data!$G$5:$G$196) -> 617.8 | F9: =SUMIF(Raw_Data!$A$5:$A$196,$A9,Raw_Data!$H$5:$H$196) -> 232.5 | G9: =SUMIF(Raw_Data!$A$5:$A$196,$A9,Raw_Data!$I$5:$I$196) -> 2335.7 | H9: =SUMIF(Raw_Data!$A$5:$A$196,$A9,Raw_Data!$J$5:$J$196) -> 1051.8 | I9: =C9+D9+E9+F9 -> 3373.9 | J9: =SUMIF(Raw_Data!$A$5:$A$196,$A9,Raw_Data!$M$5:$M$196) -> 4585.8 | L9: =(B9-B8)/B8 -> -0.1367493 | M9: =G9/B9 -> 0.5277464 | N9: =H9/B9 -> 0.23765195 | O9: =I9/B9 -> 0.76232546
A10: Jun-2025 | B10: =SUMIF(Raw_Data!$A$5:$A$196,$A10,Raw_Data!$D$5:$D$196) -> 4523.6 | C10: =SUMIF(Raw_Data!$A$5:$A$196,$A10,Raw_Data!$E$5:$E$196) -> 2102.3 | D10: =SUMIF(Raw_Data!$A$5:$A$196,$A10,Raw_Data!$F$5:$F$196) -> 437.1 | E10: =SUMIF(Raw_Data!$A$5:$A$196,$A10,Raw_Data!$G$5:$G$196) -> 632.9 | F10: =SUMIF(Raw_Data!$A$5:$A$196,$A10,Raw_Data!$H$5:$H$196) -> 241.4 | G10: =SUMIF(Raw_Data!$A$5:$A$196,$A10,Raw_Data!$I$5:$I$196) -> 2421.2 | H10: =SUMIF(Raw_Data!$A$5:$A$196,$A10,Raw_Data!$J$5:$J$196) -> 1110.3 | I10: =C10+D10+E10+F10 -> 3413.7 | J10: =SUMIF(Raw_Data!$A$5:$A$196,$A10,Raw_Data!$M$5:$M$196) -> 4579.5 | L10: =(B10-B9)/B9 -> 0.0220977 | M10: =G10/B10 -> 0.53523742 | N10: =H10/B10 -> 0.2454461 | O10: =I10/B10 -> 0.75464232
A11: Jul-2025 | B11: =SUMIF(Raw_Data!$A$5:$A$196,$A11,Raw_Data!$D$5:$D$196) -> 4681.3 | C11: =SUMIF(Raw_Data!$A$5:$A$196,$A11,Raw_Data!$E$5:$E$196) -> 2171.6 | D11: =SUMIF(Raw_Data!$A$5:$A$196,$A11,Raw_Data!$F$5:$F$196) -> 465.5 | E11: =SUMIF(Raw_Data!$A$5:$A$196,$A11,Raw_Data!$G$5:$G$196) -> 653.5 | F11: =SUMIF(Raw_Data!$A$5:$A$196,$A11,Raw_Data!$H$5:$H$196) -> 249 | G11: =SUMIF(Raw_Data!$A$5:$A$196,$A11,Raw_Data!$I$5:$I$196) -> 2509.6 | H11: =SUMIF(Raw_Data!$A$5:$A$196,$A11,Raw_Data!$J$5:$J$196) -> 1141.2 | I11: =C11+D11+E11+F11 -> 3539.6 | J11: =SUMIF(Raw_Data!$A$5:$A$196,$A11,Raw_Data!$M$5:$M$196) -> 4668.6 | L11: =(B11-B10)/B10 -> 0.034861615 | M11: =G11/B11 -> 0.5360904 | N11: =H11/B11 -> 0.24377844 | O11: =I11/B11 -> 0.75611475
A12: Aug-2025 | B12: =SUMIF(Raw_Data!$A$5:$A$196,$A12,Raw_Data!$D$5:$D$196) -> 4778.8 | C12: =SUMIF(Raw_Data!$A$5:$A$196,$A12,Raw_Data!$E$5:$E$196) -> 2234.2 | D12: =SUMIF(Raw_Data!$A$5:$A$196,$A12,Raw_Data!$F$5:$F$196) -> 452.9 | E12: =SUMIF(Raw_Data!$A$5:$A$196,$A12,Raw_Data!$G$5:$G$196) -> 672.9 | F12: =SUMIF(Raw_Data!$A$5:$A$196,$A12,Raw_Data!$H$5:$H$196) -> 252.7 | G12: =SUMIF(Raw_Data!$A$5:$A$196,$A12,Raw_Data!$I$5:$I$196) -> 2544.7 | H12: =SUMIF(Raw_Data!$A$5:$A$196,$A12,Raw_Data!$J$5:$J$196) -> 1166.1 | I12: =C12+D12+E12+F12 -> 3612.7 | J12: =SUMIF(Raw_Data!$A$5:$A$196,$A12,Raw_Data!$M$5:$M$196) -> 4931.8 | L12: =(B12-B11)/B11 -> 0.020827548 | M12: =G12/B12 -> 0.5324977 | N12: =H12/B12 -> 0.24401523 | O12: =I12/B12 -> 0.75598477
A13: Sep-2025 | B13: =SUMIF(Raw_Data!$A$5:$A$196,$A13,Raw_Data!$D$5:$D$196) -> 5039.4 | C13: =SUMIF(Raw_Data!$A$5:$A$196,$A13,Raw_Data!$E$5:$E$196) -> 2371 | D13: =SUMIF(Raw_Data!$A$5:$A$196,$A13,Raw_Data!$F$5:$F$196) -> 495.4 | E13: =SUMIF(Raw_Data!$A$5:$A$196,$A13,Raw_Data!$G$5:$G$196) -> 705.3 | F13: =SUMIF(Raw_Data!$A$5:$A$196,$A13,Raw_Data!$H$5:$H$196) -> 269.5 | G13: =SUMIF(Raw_Data!$A$5:$A$196,$A13,Raw_Data!$I$5:$I$196) -> 2668.4 | H13: =SUMIF(Raw_Data!$A$5:$A$196,$A13,Raw_Data!$J$5:$J$196) -> 1198.2 | I13: =C13+D13+E13+F13 -> 3841.2 | J13: =SUMIF(Raw_Data!$A$5:$A$196,$A13,Raw_Data!$M$5:$M$196) -> 5180.4 | L13: =(B13-B12)/B12 -> 0.054532519 | M13: =G13/B13 -> 0.52950748 | N13: =H13/B13 -> 0.2377664 | O13: =I13/B13 -> 0.7622336
A14: Oct-2025 | B14: =SUMIF(Raw_Data!$A$5:$A$196,$A14,Raw_Data!$D$5:$D$196) -> 5100.7 | C14: =SUMIF(Raw_Data!$A$5:$A$196,$A14,Raw_Data!$E$5:$E$196) -> 2371.5 | D14: =SUMIF(Raw_Data!$A$5:$A$196,$A14,Raw_Data!$F$5:$F$196) -> 488.8 | E14: =SUMIF(Raw_Data!$A$5:$A$196,$A14,Raw_Data!$G$5:$G$196) -> 718 | F14: =SUMIF(Raw_Data!$A$5:$A$196,$A14,Raw_Data!$H$5:$H$196) -> 270.4 | G14: =SUMIF(Raw_Data!$A$5:$A$196,$A14,Raw_Data!$I$5:$I$196) -> 2729.2 | H14: =SUMIF(Raw_Data!$A$5:$A$196,$A14,Raw_Data!$J$5:$J$196) -> 1251.9 | I14: =C14+D14+E14+F14 -> 3848.7 | J14: =SUMIF(Raw_Data!$A$5:$A$196,$A14,Raw_Data!$M$5:$M$196) -> 5346.4 | L14: =(B14-B13)/B13 -> 0.012164147 | M14: =G14/B14 -> 0.53506381 | N14: =H14/B14 -> 0.2454369 | O14: =I14/B14 -> 0.75454349
A15: Nov-2025 | B15: =SUMIF(Raw_Data!$A$5:$A$196,$A15,Raw_Data!$D$5:$D$196) -> 6091.8 | C15: =SUMIF(Raw_Data!$A$5:$A$196,$A15,Raw_Data!$E$5:$E$196) -> 2862.5 | D15: =SUMIF(Raw_Data!$A$5:$A$196,$A15,Raw_Data!$F$5:$F$196) -> 608.1 | E15: =SUMIF(Raw_Data!$A$5:$A$196,$A15,Raw_Data!$G$5:$G$196) -> 854.7 | F15: =SUMIF(Raw_Data!$A$5:$A$196,$A15,Raw_Data!$H$5:$H$196) -> 326.1 | G15: =SUMIF(Raw_Data!$A$5:$A$196,$A15,Raw_Data!$I$5:$I$196) -> 3229.3 | H15: =SUMIF(Raw_Data!$A$5:$A$196,$A15,Raw_Data!$J$5:$J$196) -> 1440.4 | I15: =C15+D15+E15+F15 -> 4651.4 | J15: =SUMIF(Raw_Data!$A$5:$A$196,$A15,Raw_Data!$M$5:$M$196) -> 6147.4 | L15: =(B15-B14)/B14 -> 0.19430666 | M15: =G15/B15 -> 0.53010604 | N15: =H15/B15 -> 0.236449 | O15: =I15/B15 -> 0.763551
A16: Dec-2025 | B16: =SUMIF(Raw_Data!$A$5:$A$196,$A16,Raw_Data!$D$5:$D$196) -> 6560.8 | C16: =SUMIF(Raw_Data!$A$5:$A$196,$A16,Raw_Data!$E$5:$E$196) -> 2992.1 | D16: =SUMIF(Raw_Data!$A$5:$A$196,$A16,Raw_Data!$F$5:$F$196) -> 655.4 | E16: =SUMIF(Raw_Data!$A$5:$A$196,$A16,Raw_Data!$G$5:$G$196) -> 916.4 | F16: =SUMIF(Raw_Data!$A$5:$A$196,$A16,Raw_Data!$H$5:$H$196) -> 350.9 | G16: =SUMIF(Raw_Data!$A$5:$A$196,$A16,Raw_Data!$I$5:$I$196) -> 3568.7 | H16: =SUMIF(Raw_Data!$A$5:$A$196,$A16,Raw_Data!$J$5:$J$196) -> 1646 | I16: =C16+D16+E16+F16 -> 4914.8 | J16: =SUMIF(Raw_Data!$A$5:$A$196,$A16,Raw_Data!$M$5:$M$196) -> 6642.4 | L16: =(B16-B15)/B15 -> 0.076988739 | M16: =G16/B16 -> 0.54394281 | N16: =H16/B16 -> 0.25088404 | O16: =I16/B16 -> 0.74911596
A17: TOTAL | B17: =SUM(B5:B16) -> 59186.7 | C17: =SUM(C5:C16) -> 27568.6 | D17: =SUM(D5:D16) -> 5773 | E17: =SUM(E5:E16) -> 8303 | F17: =SUM(F5:F16) -> 3151 | G17: =SUM(G5:G16) -> 31618.5 | H17: =SUM(H5:H16) -> 14390.6 | I17: =SUM(I5:I16) -> 44795.6 | J17: =SUM(J5:J16) -> 60297.3

Sheet Service_Summary
A1: Profitability by Service Line
A2: Annual aggregation by service category with margins, CAC and ROAS (IDR millions).
A4: Service Category | B4: Revenue | C4: Gross Profit | D4: Net Profit | E4: GP Margin % | F4: NP Margin % | G4: Avg CAC | H4: Avg ROAS
A5: Influencer Marketing | B5: =SUMIF(Raw_Data!$B$5:$B$196,$A5,Raw_Data!$D$5:$D$196) -> 12855.8 | C5: =SUMIF(Raw_Data!$B$5:$B$196,$A5,Raw_Data!$I$5:$I$196) -> 7456.3 | D5: =SUMIF(Raw_Data!$B$5:$B$196,$A5,Raw_Data!$J$5:$J$196) -> 3959.2 | E5: =C5/B5 -> 0.57999502 | F5: =D5/B5 -> 0.30796994 | G5: =AVERAGEIF(Raw_Data!$B$5:$B$196,$A5,Raw_Data!$K$5:$K$196) -> 3.2414583 | H5: =AVERAGEIF(Raw_Data!$B$5:$B$196,$A5,Raw_Data!$L$5:$L$196) -> 4.1666667
A6: Ads Management | B6: =SUMIF(Raw_Data!$B$5:$B$196,$A6,Raw_Data!$D$5:$D$196) -> 20605.9 | C6: =SUMIF(Raw_Data!$B$5:$B$196,$A6,Raw_Data!$I$5:$I$196) -> 9208.6 | D6: =SUMIF(Raw_Data!$B$5:$B$196,$A6,Raw_Data!$J$5:$J$196) -> 4229.7 | E6: =C6/B6 -> 0.44689142 | F6: =D6/B6 -> 0.20526645 | G6: =AVERAGEIF(Raw_Data!$B$5:$B$196,$A6,Raw_Data!$K$5:$K$196) -> 2.4522917 | H6: =AVERAGEIF(Raw_Data!$B$5:$B$196,$A6,Raw_Data!$L$5:$L$196) -> 5.53625
A7: E-commerce Enablement | B7: =SUMIF(Raw_Data!$B$5:$B$196,$A7,Raw_Data!$D$5:$D$196) -> 16464.8 | C7: =SUMIF(Raw_Data!$B$5:$B$196,$A7,Raw_Data!$I$5:$I$196) -> 8495.9 | D7: =SUMIF(Raw_Data!$B$5:$B$196,$A7,Raw_Data!$J$5:$J$196) -> 4022 | E7: =C7/B7 -> 0.51600384 | F7: =D7/B7 -> 0.2442787 | G7: =AVERAGEIF(Raw_Data!$B$5:$B$196,$A7,Raw_Data!$K$5:$K$196) -> 4.0595833 | H7: =AVERAGEIF(Raw_Data!$B$5:$B$196,$A7,Raw_Data!$L$5:$L$196) -> 3.7672917
A8: SaaS Creator Platform | B8: =SUMIF(Raw_Data!$B$5:$B$196,$A8,Raw_Data!$D$5:$D$196) -> 9260.2 | C8: =SUMIF(Raw_Data!$B$5:$B$196,$A8,Raw_Data!$I$5:$I$196) -> 6457.7 | D8: =SUMIF(Raw_Data!$B$5:$B$196,$A8,Raw_Data!$J$5:$J$196) -> 2179.7 | E8: =C8/B8 -> 0.69736075 | F8: =D8/B8 -> 0.23538369 | G8: =AVERAGEIF(Raw_Data!$B$5:$B$196,$A8,Raw_Data!$K$5:$K$196) -> 5.4385417 | H8: =AVERAGEIF(Raw_Data!$B$5:$B$196,$A8,Raw_Data!$L$5:$L$196) -> 3.2566667
A9: TOTAL / AVG | B9: =SUM(B5:B8) -> 59186.7 | C9: =SUM(C5:C8) -> 31618.5 | D9: =SUM(D5:D8) -> 14390.6 | E9: =C9/B9 -> 0.5342163 | F9: =D9/B9 -> 0.24313908 | G9: =AVERAGE(G5:G8) -> 3.7979687 | H9: =AVERAGE(H5:H8) -> 4.1817187

Sheet Cost_Breakdown
A1: Operational Cost Breakdown
A2: Annual cost composition by category - basis for cost-saving analysis (IDR millions).
A4: Cost Category | B4: Annual Amount | C4: % of Total Cost | D4: % of Revenue
A5: Operational Cost | B5: =SUM(Raw_Data!$E$5:$E$196) -> 27568.6 | C5: =B5/$B$9 -> 0.61543098 | D5: =B5/SUM(Raw_Data!$D$5:$D$196) -> 0.46579046
A6: Marketing Spend | B6: =SUM(Raw_Data!$F$5:$F$196) -> 5773 | C6: =B6/$B$9 -> 0.12887426 | D6: =B6/SUM(Raw_Data!$D$5:$D$196) -> 0.097538805
A7: Employee Cost | B7: =SUM(Raw_Data!$G$5:$G$196) -> 8303 | C7: =B7/$B$9 -> 0.18535303 | D7: =B7/SUM(Raw_Data!$D$5:$D$196) -> 0.1402849
A8: Software Subscription Cost | B8: =SUM(Raw_Data!$H$5:$H$196) -> 3151 | C8: =B8/$B$9 -> 0.07034173 | D8: =B8/SUM(Raw_Data!$D$5:$D$196) -> 0.053238312
A9: TOTAL COST | B9: =SUM(B5:B8) -> 44795.6 | C9: =SUM(C5:C8) -> 1 | D9: =B9/SUM(Raw_Data!$D$5:$D$196) -> 0.75685247

Sheet Budget_vs_Actual
A1: Budget vs Actual Analysis
A2: Monthly planned vs actual spend with variance and utilization (IDR millions).
A4: Month | B4: Budget | C4: Actual Spending | D4: Variance | E4: Variance % | F4: Status
A5: Jan-2025 | B5: =SUMIF(Raw_Data!$A$5:$A$196,$A5,Raw_Data!$M$5:$M$196) -> 4049.6 | C5: =SUMIF(Raw_Data!$A$5:$A$196,$A5,Raw_Data!$N$5:$N$196) -> 3056 | D5: =B5-C5 -> 993.6 | E5: =(B5-C5)/B5 -> 0.24535757 | F5: =IF(C5<=B5,"Under Budget","Over Budget") -> Under Budget
A6: Feb-2025 | B6: =SUMIF(Raw_Data!$A$5:$A$196,$A6,Raw_Data!$M$5:$M$196) -> 4172.8 | C6: =SUMIF(Raw_Data!$A$5:$A$196,$A6,Raw_Data!$N$5:$N$196) -> 3177.8 | D6: =B6-C6 -> 995 | E6: =(B6-C6)/B6 -> 0.238449 | F6: =IF(C6<=B6,"Under Budget","Over Budget") -> Under Budget
A7: Mar-2025 | B7: =SUMIF(Raw_Data!$A$5:$A$196,$A7,Raw_Data!$M$5:$M$196) -> 4826.2 | C7: =SUMIF(Raw_Data!$A$5:$A$196,$A7,Raw_Data!$N$5:$N$196) -> 3745.6 | D7: =B7-C7 -> 1080.6 | E7: =(B7-C7)/B7 -> 0.22390286 | F7: =IF(C7<=B7,"Under Budget","Over Budget") -> Under Budget
A8: Apr-2025 | B8: =SUMIF(Raw_Data!$A$5:$A$196,$A8,Raw_Data!$M$5:$M$196) -> 5166.4 | C8: =SUMIF(Raw_Data!$A$5:$A$196,$A8,Raw_Data!$N$5:$N$196) -> 3870.5 | D8: =B8-C8 -> 1295.9 | E8: =(B8-C8)/B8 -> 0.2508323 | F8: =IF(C8<=B8,"Under Budget","Over Budget") -> Under Budget
A9: May-2025 | B9: =SUMIF(Raw_Data!$A$5:$A$196,$A9,Raw_Data!$M$5:$M$196) -> 4585.8 | C9: =SUMIF(Raw_Data!$A$5:$A$196,$A9,Raw_Data!$N$5:$N$196) -> 3454.7 | D9: =B9-C9 -> 1131.1 | E9: =(B9-C9)/B9 -> 0.24665271 | F9: =IF(C9<=B9,"Under Budget","Over Budget") -> Under Budget
A10: Jun-2025 | B10: =SUMIF(Raw_Data!$A$5:$A$196,$A10,Raw_Data!$M$5:$M$196) -> 4579.5 | C10: =SUMIF(Raw_Data!$A$5:$A$196,$A10,Raw_Data!$N$5:$N$196) -> 3425.7 | D10: =B10-C10 -> 1153.8 | E10: =(B10-C10)/B10 -> 0.2519489 | F10: =IF(C10<=B10,"Under Budget","Over Budget") -> Under Budget
A11: Jul-2025 | B11: =SUMIF(Raw_Data!$A$5:$A$196,$A11,Raw_Data!$M$5:$M$196) -> 4668.6 | C11: =SUMIF(Raw_Data!$A$5:$A$196,$A11,Raw_Data!$N$5:$N$196) -> 3634.8 | D11: =B11-C11 -> 1033.8 | E11: =(B11-C11)/B11 -> 0.22143683 | F11: =IF(C11<=B11,"Under Budget","Over Budget") -> Under Budget
A12: Aug-2025 | B12: =SUMIF(Raw_Data!$A$5:$A$196,$A12,Raw_Data!$M$5:$M$196) -> 4931.8 | C12: =SUMIF(Raw_Data!$A$5:$A$196,$A12,Raw_Data!$N$5:$N$196) -> 3604.2 | D12: =B12-C12 -> 1327.6 | E12: =(B12-C12)/B12 -> 0.26919178 | F12: =IF(C12<=B12,"Under Budget","Over Budget") -> Under Budget
A13: Sep-2025 | B13: =SUMIF(Raw_Data!$A$5:$A$196,$A13,Raw_Data!$M$5:$M$196) -> 5180.4 | C13: =SUMIF(Raw_Data!$A$5:$A$196,$A13,Raw_Data!$N$5:$N$196) -> 3868.2 | D13: =B13-C13 -> 1312.2 | E13: =(B13-C13)/B13 -> 0.2533009 | F13: =IF(C13<=B13,"Under Budget","Over Budget") -> Under Budget
A14: Oct-2025 | B14: =SUMIF(Raw_Data!$A$5:$A$196,$A14,Raw_Data!$M$5:$M$196) -> 5346.4 | C14: =SUMIF(Raw_Data!$A$5:$A$196,$A14,Raw_Data!$N$5:$N$196) -> 3935.3 | D14: =B14-C14 -> 1411.1 | E14: =(B14-C14)/B14 -> 0.26393461 | F14: =IF(C14<=B14,"Under Budget","Over Budget") -> Under Budget
A15: Nov-2025 | B15: =SUMIF(Raw_Data!$A$5:$A$196,$A15,Raw_Data!$M$5:$M$196) -> 6147.4 | C15: =SUMIF(Raw_Data!$A$5:$A$196,$A15,Raw_Data!$N$5:$N$196) -> 4777.9 | D15: =B15-C15 -> 1369.5 | E15: =(B15-C15)/B15 -> 0.22277711 | F15: =IF(C15<=B15,"Under Budget","Over Budget") -> Under Budget
A16: Dec-2025 | B16: =SUMIF(Raw_Data!$A$5:$A$196,$A16,Raw_Data!$M$5:$M$196) -> 6642.4 | C16: =SUMIF(Raw_Data!$A$5:$A$196,$A16,Raw_Data!$N$5:$N$196) -> 5056.4 | D16: =B16-C16 -> 1586 | E16: =(B16-C16)/B16 -> 0.23876912 | F16: =IF(C16<=B16,"Under Budget","Over Budget") -> Under Budget
A17: TOTAL | B17: =SUM(B5:B16) -> 60297.3 | C17: =SUM(C5:C16) -> 45607.1 | D17: =SUM(D5:D16) -> 14690.2 | E17: =D17/B17 -> 0.24362948 | F17: =IF(C17<=B17,"Under Budget","Over Budget") -> Under Budget

Sheet Forecast
A1: Revenue & Profit Forecast
A2: 3-month projection using TREND() linear regression on 12 historical months (IDR millions).
A4: Period | B4: Month | C4: Revenue | D4: Net Profit | E4: Type | G4: Rev Actual | H4: Rev Forecast
A5: 1 | B5: Jan-2025 | C5: =Monthly_Summary!B5 -> 3945.6 | D5: =Monthly_Summary!H5 -> 943.2 | E5: Actual | G5: =C5 -> 3945.6
A6: 2 | B6: Feb-2025 | C6: =Monthly_Summary!B6 -> 4108 | D6: =Monthly_Summary!H6 -> 983.5 | E6: Actual | G6: =C6 -> 4108
A7: 3 | B7: Mar-2025 | C7: =Monthly_Summary!B7 -> 4804 | D7: =Monthly_Summary!H7 -> 1148.1 | E7: Actual | G7: =C7 -> 4804
A8: 4 | B8: Apr-2025 | C8: =Monthly_Summary!B8 -> 5126.9 | D8: =Monthly_Summary!H8 -> 1309.9 | E8: Actual | G8: =C8 -> 5126.9
A9: 5 | B9: May-2025 | C9: =Monthly_Summary!B9 -> 4425.8 | D9: =Monthly_Summary!H9 -> 1051.8 | E9: Actual | G9: =C9 -> 4425.8
A10: 6 | B10: Jun-2025 | C10: =Monthly_Summary!B10 -> 4523.6 | D10: =Monthly_Summary!H10 -> 1110.3 | E10: Actual | G10: =C10 -> 4523.6
A11: 7 | B11: Jul-2025 | C11: =Monthly_Summary!B11 -> 4681.3 | D11: =Monthly_Summary!H11 -> 1141.2 | E11: Actual | G11: =C11 -> 4681.3
A12: 8 | B12: Aug-2025 | C12: =Monthly_Summary!B12 -> 4778.8 | D12: =Monthly_Summary!H12 -> 1166.1 | E12: Actual | G12: =C12 -> 4778.8
A13: 9 | B13: Sep-2025 | C13: =Monthly_Summary!B13 -> 5039.4 | D13: =Monthly_Summary!H13 -> 1198.2 | E13: Actual | G13: =C13 -> 5039.4
A14: 10 | B14: Oct-2025 | C14: =Monthly_Summary!B14 -> 5100.7 | D14: =Monthly_Summary!H14 -> 1251.9 | E14: Actual | G14: =C14 -> 5100.7
A15: 11 | B15: Nov-2025 | C15: =Monthly_Summary!B15 -> 6091.8 | D15: =Monthly_Summary!H15 -> 1440.4 | E15: Actual | G15: =C15 -> 6091.8
A16: 12 | B16: Dec-2025 | C16: =Monthly_Summary!B16 -> 6560.8 | D16: =Monthly_Summary!H16 -> 1646 | E16: Actual | G16: =C16 -> 6560.8 | H16: =C16 -> 6560.8
A17: 13 | B17: Jan-2026 | C17: =TREND($C$5:$C$16,$A$5:$A$16,A17) -> 6056.7136 | D17: =TREND($D$5:$D$16,$A$5:$A$16,A17) -> 1480.6894 | E17: Forecast | H17: =C17 -> 6056.7136
A18: 14 | B18: Feb-2026 | C18: =TREND($C$5:$C$16,$A$5:$A$16,A18) -> 6229.7119 | D18: =TREND($D$5:$D$16,$A$5:$A$16,A18) -> 1523.9929 | E18: Forecast | H18: =C18 -> 6229.7119
A19: 15 | B19: Mar-2026 | C19: =TREND($C$5:$C$16,$A$5:$A$16,A19) -> 6402.7101 | D19: =TREND($D$5:$D$16,$A$5:$A$16,A19) -> 1567.2964 | E19: Forecast | H19: =C19 -> 6402.7101

Sheet KPI_Metrics
A1: Headline KPI Metrics
A2: Company-wide annual performance indicators.
A4: KPI | B4: Value
A5: Total Revenue (IDR mil) | B5: =Monthly_Summary!B17 -> 59186.7
A6: Total Gross Profit (IDR mil) | B6: =Monthly_Summary!G17 -> 31618.5
A7: Total Net Profit (IDR mil) | B7: =Monthly_Summary!H17 -> 14390.6
A8: Gross Profit Margin | B8: =Monthly_Summary!G17/Monthly_Summary!B17 -> 0.5342163
A9: Net Profit Margin | B9: =Monthly_Summary!H17/Monthly_Summary!B17 -> 0.24313908
A10: Operating Expense Ratio | B10: =Monthly_Summary!I17/Monthly_Summary!B17 -> 0.75685247
A11: Revenue Growth (Jan→Dec) | B11: =(Monthly_Summary!B16-Monthly_Summary!B5)/Monthly_Summary!B5 -> 0.66281427
A12: Average CAC (IDR mil) | B12: =AVERAGE(Raw_Data!$K$5:$K$196) -> 3.7979688
A13: Average ROAS (x) | B13: =AVERAGE(Raw_Data!$L$5:$L$196) -> 4.1817188
A14: Total Budget (IDR mil) | B14: =SUM(Raw_Data!$M$5:$M$196) -> 60297.3
A15: Total Actual Spend (IDR mil) | B15: =SUM(Raw_Data!$N$5:$N$196) -> 45607.1
A16: Budget Utilization | B16: =SUM(Raw_Data!$N$5:$N$196)/SUM(Raw_Data!$M$5:$M$196) -> 0.75637052
